model_json/__init__.py
model_json/__main__.py
model_json/py.typed
model_json-0.0.0.dist-info/entry_points.txt
model_json-0.0.0.dist-info/LICENSE
model_json-0.0.0.dist-info/WHEEL
model_json-0.0.0.dist-info/METADATA
model_json-0.0.0.dist-info/RECORD
