Metadata-Version: 2.1
Name: model-json
Version: 0.0.0
Summary: Model Json
Home-page: https://github.com/gagan-preet-singh/model-json
License: MIT
Author: Gagan Preet Singh
Author-email: s.gagan.preet@gmail.com
Requires-Python: >=3.7,<4.0
Classifier: Development Status :: 2 - Pre-Alpha
Classifier: License :: OSI Approved :: MIT License
Classifier: Programming Language :: Python :: 3
Classifier: Programming Language :: Python :: 3.10
Classifier: Programming Language :: Python :: 3.7
Classifier: Programming Language :: Python :: 3.8
Classifier: Programming Language :: Python :: 3.9
Requires-Dist: click (>=8.0.1)
Project-URL: Changelog, https://github.com/gagan-preet-singh/model-json/releases
Project-URL: Documentation, https://model-json.readthedocs.io
Project-URL: Repository, https://github.com/gagan-preet-singh/model-json
